elastictools/__init__.py
elastictools/doctools.py
elastictools/indextools.py
btls3-0.1003.1.dist-info/LICENSE.txt
btls3-0.1003.1.dist-info/METADATA
btls3-0.1003.1.dist-info/WHEEL
btls3-0.1003.1.dist-info/top_level.txt
btls3-0.1003.1.dist-info/RECORD
