Metadata-Version: 2.1
Name: btls3
Version: 0.1003.1
Summary: Useful tools to work with Elastic stack in Python
Home-page: https://github.com/ncthuc/elastictools
Author: Thuc Nguyen
Author-email: gthuc.nguyen@gmail.com
License: MIT
Download-URL: https://pypi.org/project/elastictools/
Keywords: Elastic,ElasticSearch,Elastic Stack,Python 3,Elastic 7
Platform: UNKNOWN
Requires-Dist: elasticsearch (>=7.0.2)
Requires-Dist: jinja2
